LICENSE
MANIFEST.in
README.md
setup.py
nb_service_ntt/__init__.py
nb_service_ntt/admin.py
nb_service_ntt/choices.py
nb_service_ntt/filters.py
nb_service_ntt/forms.py
nb_service_ntt/models.py
nb_service_ntt/navigation.py
nb_service_ntt/signals.py
nb_service_ntt/tables.py
nb_service_ntt/urls.py
nb_service_ntt/utils.py
nb_service_ntt/version.py
nb_service_ntt/views.py
nb_service_ntt/views_2_x.py
nb_service_ntt/views_3_x.py
nb_service_ntt.egg-info/PKG-INFO
nb_service_ntt.egg-info/SOURCES.txt
nb_service_ntt.egg-info/dependency_links.txt
nb_service_ntt.egg-info/top_level.txt
nb_service_ntt/api/__init__.py
nb_service_ntt/api/serializers.py
nb_service_ntt/api/urls.py
nb_service_ntt/api/views.py
nb_service_ntt/migrations/0001_initial.py
nb_service_ntt/migrations/__init__.py
nb_service_ntt/static/nb_service_ntt/export_svg.js
nb_service_ntt/static/nb_service_ntt/mermaid.min.js
nb_service_ntt/static/nb_service_ntt/mermaid.min.js.map
nb_service_ntt/templates/nb_service_ntt/2.x/custom_list.html
nb_service_ntt/templates/nb_service_ntt/2.x/obj_edit.html
nb_service_ntt/templates/nb_service_ntt/2.x/Application/application_objs.html
nb_service_ntt/templates/nb_service_ntt/2.x/Application/application_view.html
nb_service_ntt/templates/nb_service_ntt/2.x/IC/ic_edit.html
nb_service_ntt/templates/nb_service_ntt/2.x/IC/inc/ic_table.html
nb_service_ntt/templates/nb_service_ntt/2.x/Relation/inc/relation_table.html
nb_service_ntt/templates/nb_service_ntt/2.x/service/service_IC_view.html
nb_service_ntt/templates/nb_service_ntt/2.x/service/service_Relation_view.html
nb_service_ntt/templates/nb_service_ntt/2.x/service/service_diagram_view.html
nb_service_ntt/templates/nb_service_ntt/2.x/service/service_view.html
nb_service_ntt/templates/nb_service_ntt/3.x/custom_list.html
nb_service_ntt/templates/nb_service_ntt/3.x/custom_list_3.4.html
nb_service_ntt/templates/nb_service_ntt/3.x/obj_edit.html
nb_service_ntt/templates/nb_service_ntt/3.x/Application/application_ChangeLog.html
nb_service_ntt/templates/nb_service_ntt/3.x/Application/application_objs.html
nb_service_ntt/templates/nb_service_ntt/3.x/Application/application_view.html
