Metadata-Version: 2.1
Name: nb-service-ntt
Version: 1.0.21
Summary: UNKNOWN
Home-page: UNKNOWN
Author: Renato Almeida de Oliveira and Brandon Crenshaw
Author-email: crench3@gmail.com
License: UNKNOWN
Platform: UNKNOWN
Classifier: Development Status :: 2 - Pre-Alpha
Classifier: Framework :: Django
Classifier: Programming Language :: Python :: 3
License-File: LICENSE
